tools.py
sztestlib/--init--.py
sztestlib/werwq.py
gmzyeahye426-1.0.4.dist-info/LICENSE.txt
gmzyeahye426-1.0.4.dist-info/METADATA
gmzyeahye426-1.0.4.dist-info/WHEEL
gmzyeahye426-1.0.4.dist-info/top_level.txt
gmzyeahye426-1.0.4.dist-info/RECORD
