Metadata-Version: 2.1
Name: gmzyeahye426
Version: 1.0.4
Summary: a function to input this datas
Home-page: https://github.com/GMZ-426/Python_code
Author: GMZ-426
Author-email: 1847394932@qq.com
License: MIT
Platform: UNKNOWN
